{
    "instance_name": "mamut-tokyo-n10-wave-light-poi",
    "routes": [
        [8, 9, 3, 5, 4, 1, 10, 6, 2, 7]
    ],
    "cost": 10047.844942020261,
    "metadata": {
        "source": "kayros 0.4.0.dev0 TD-ILS (seed=42, time_limit=30.0s)",
        "validated_by": "mamut-routing-lib td Duration checker",
        "date": "2026-07-08T16:30:47",
        "route_durations": [10047.844942020261],
        "route_departure_times": [0.0],
        "authors": "Florian Rascoussier (0nyr)",
        "validated_cost": 10047.844942020261,
        "validated_num_routes": 1
    },
    "objective_function": "Duration"
}
